[
  {
    "event_id": "RE-20260410-001",
    "event_name": "生椰乳温度波动导致口感异常",
    "product_id": "P02",
    "issue_type": "IT04",
    "risk_level": "low",
    "risk_score": 3,
    "suspected_cause": "华东仓冷链设备短暂故障，部分生椰乳温度升至8°C以上，导致口感略有变化",
    "linked_supplier": ["SUP03"],
    "linked_batch": ["BAT-20260410-001"],
    "recommended_action": ["CA-20260420-001"],
    "raw_feedback_count": 12,
    "feedback_keywords": ["味道不对", "不新鲜", "口感差"],
    "aggregated_at": "2026-04-10T14:00:00",
    "detected_at": "2026-04-09T10:00:00",
    "escalated_at": "",
    "controlled_at": "2026-04-10T16:00:00",
    "resolved_at": "2026-04-12T18:00:00",
    "lifecycle_stage": "resolved"
  },
  {
    "event_id": "RE-20260420-001",
    "event_name": "椰子果肉氧化变紫引发消费者投诉",
    "product_id": "P02",
    "issue_type": "IT05",
    "risk_level": "medium",
    "risk_score": 5,
    "suspected_cause": "椰子果肉中多酚类物质接触空气后正常氧化反应，消费者误认为变质",
    "linked_supplier": ["SUP03", "SUP04"],
    "linked_batch": ["BAT-20260410-001"],
    "recommended_action": ["CA-20260420-001", "CA-20260420-002"],
    "raw_feedback_count": 38,
    "feedback_keywords": ["发紫", "变色", "颜色不正常", "是不是坏了", "氧化了", "不新鲜", "紫色"],
    "aggregated_at": "2026-04-20T10:30:00",
    "detected_at": "2026-04-18T09:15:00",
    "escalated_at": "2026-04-19T14:00:00",
    "controlled_at": "2026-04-20T16:00:00",
    "resolved_at": "2026-04-25T18:00:00",
    "lifecycle_stage": "resolved"
  },
  {
    "event_id": "RE-20260428-001",
    "event_name": "一整颗生椰椰乳沉淀分层投诉",
    "product_id": "P02",
    "issue_type": "IT03",
    "risk_level": "medium",
    "risk_score": 4,
    "suspected_cause": "椰乳中蛋白质在长时间静置后自然沉淀，门店未在出杯前充分摇匀",
    "linked_supplier": ["SUP03"],
    "linked_batch": ["BAT-20260410-001"],
    "recommended_action": ["CA-20260420-001"],
    "raw_feedback_count": 15,
    "feedback_keywords": ["沉淀", "分层", "椰乳", "像豆腐渣"],
    "aggregated_at": "2026-04-28T11:00:00",
    "detected_at": "2026-04-26T09:00:00",
    "escalated_at": "",
    "controlled_at": "2026-04-28T14:00:00",
    "resolved_at": "2026-05-02T18:00:00",
    "lifecycle_stage": "resolved"
  },
  {
    "event_id": "RE-20260508-001",
    "event_name": "好柿成双柿子果肉氧化变色",
    "product_id": "P01",
    "issue_type": "IT02",
    "risk_level": "medium",
    "risk_score": 4,
    "suspected_cause": "柿子果肉切开后暴露空气时间过长导致表面氧化褐变，影响外观",
    "linked_supplier": ["SUP02"],
    "linked_batch": ["BAT-20260501-001"],
    "recommended_action": ["CA-20260515-003", "CA-20260515-005"],
    "raw_feedback_count": 18,
    "feedback_keywords": ["变色", "发黑", "不新鲜", "氧化", "颜色不好"],
    "aggregated_at": "2026-05-08T10:00:00",
    "detected_at": "2026-05-06T14:00:00",
    "escalated_at": "",
    "controlled_at": "2026-05-08T15:00:00",
    "resolved_at": "2026-05-12T18:00:00",
    "lifecycle_stage": "resolved"
  },
  {
    "event_id": "RE-20260515-001",
    "event_name": "好柿成双涩味异常",
    "product_id": "P01",
    "issue_type": "IT01",
    "risk_level": "high",
    "risk_score": 10,
    "suspected_cause": "供应商B提供的柿子成熟度不足，单宁含量偏高导致明显涩味",
    "linked_supplier": ["SUP02"],
    "linked_batch": ["BAT-20260428-001", "BAT-20260501-001"],
    "recommended_action": ["CA-20260515-001", "CA-20260515-002", "CA-20260515-003", "CA-20260515-004", "CA-20260515-005"],
    "raw_feedback_count": 68,
    "feedback_keywords": ["涩", "巨涩", "没熟", "发苦", "口感差", "每一口都涩"],
    "aggregated_at": "2026-05-15T11:00:00",
    "detected_at": "2026-05-12T08:30:00",
    "escalated_at": "2026-05-13T10:00:00",
    "controlled_at": "2026-05-15T15:00:00",
    "resolved_at": "",
    "lifecycle_stage": "controlled"
  },
  {
    "event_id": "RE-20260520-001",
    "event_name": "好柿成双脆啵啵口感变硬投诉",
    "product_id": "P01",
    "issue_type": "IT10",
    "risk_level": "low",
    "risk_score": 3,
    "suspected_cause": "脆啵啵小料在冷藏超时后质地变硬，影响口感体验",
    "linked_supplier": ["SUP01"],
    "linked_batch": ["BAT-20260505-001"],
    "recommended_action": ["CA-20260515-005"],
    "raw_feedback_count": 10,
    "feedback_keywords": ["太硬", "口感差", "啵啵", "不Q弹"],
    "aggregated_at": "2026-05-20T10:00:00",
    "detected_at": "2026-05-18T14:00:00",
    "escalated_at": "",
    "controlled_at": "2026-05-20T14:00:00",
    "resolved_at": "2026-05-22T18:00:00",
    "lifecycle_stage": "resolved"
  },
  {
    "event_id": "RE-20260525-001",
    "event_name": "好柿成双茶底过萃苦涩反馈",
    "product_id": "P01",
    "issue_type": "IT11",
    "risk_level": "low",
    "risk_score": 3,
    "suspected_cause": "部分门店茉莉绿茶底浸泡时间过长导致苦涩味，叠加柿子涩味问题加重负面感受",
    "linked_supplier": ["SUP01"],
    "linked_batch": ["BAT-20260505-001"],
    "recommended_action": ["CA-20260515-005"],
    "raw_feedback_count": 14,
    "feedback_keywords": ["苦涩", "像中药", "茶味太重", "苦"],
    "aggregated_at": "2026-05-25T10:00:00",
    "detected_at": "2026-05-23T09:00:00",
    "escalated_at": "",
    "controlled_at": "2026-05-25T14:00:00",
    "resolved_at": "2026-05-28T18:00:00",
    "lifecycle_stage": "resolved"
  },
  {
    "event_id": "RE-20260525-002",
    "event_name": "hello苹果茉莉配方测试阶段絮状物预警",
    "product_id": "P03",
    "issue_type": "IT03",
    "risk_level": "medium_high",
    "risk_score": 8,
    "suspected_cause": "内部配方测试中发现：苹果汁pH值3.8时与牛奶混合后30分钟出现絮状物，温度>15°C时加速",
    "linked_supplier": ["SUP05", "SUP06"],
    "linked_batch": ["BAT-20260518-001", "BAT-20260518-002"],
    "recommended_action": ["CA-20260601-001", "CA-20260601-002"],
    "raw_feedback_count": 8,
    "feedback_keywords": ["絮状物", "沉淀", "结块", "分层"],
    "aggregated_at": "2026-05-25T09:00:00",
    "detected_at": "2026-05-24T16:00:00",
    "escalated_at": "",
    "controlled_at": "",
    "resolved_at": "",
    "lifecycle_stage": "detected"
  },
  {
    "event_id": "RE-20260601-001",
    "event_name": "hello苹果茉莉新品上市风险预警",
    "product_id": "P03",
    "issue_type": "IT03",
    "risk_level": "medium_high",
    "risk_score": 8,
    "suspected_cause": "基于历史案例分析：苹果汁中果酸在pH<4.0、温度>15°C条件下可能导致牛奶蛋白质变性，产生絮状物。新品尚未上市，通过小规模测试数据+知识规则匹配预测此风险",
    "linked_supplier": ["SUP05", "SUP06"],
    "linked_batch": ["BAT-20260518-001", "BAT-20260518-002"],
    "recommended_action": ["CA-20260601-001", "CA-20260601-002"],
    "raw_feedback_count": 32,
    "feedback_keywords": ["絮状物", "沉淀", "分层", "结块", "颗粒", "像坏了"],
    "aggregated_at": "2026-06-01T09:00:00",
    "detected_at": "2026-05-30T16:45:00",
    "escalated_at": "",
    "controlled_at": "",
    "resolved_at": "",
    "lifecycle_stage": "detected"
  },
  {
    "event_id": "RE-20260605-001",
    "event_name": "hello苹果茉莉苹果汁氧化褐变预警",
    "product_id": "P03",
    "issue_type": "IT02",
    "risk_level": "medium",
    "risk_score": 5,
    "suspected_cause": "测试中发现苹果汁切开后2小时内出现明显褐变，影响产品外观和消费者接受度；茉莉茶底长时间暴露也存在氧化变味风险",
    "linked_supplier": ["SUP05"],
    "linked_batch": ["BAT-20260518-001"],
    "recommended_action": ["CA-20260601-001", "CA-20260601-002"],
    "raw_feedback_count": 6,
    "feedback_keywords": ["变色", "发黑", "氧化", "不新鲜", "褐变"],
    "aggregated_at": "2026-06-05T10:00:00",
    "detected_at": "2026-06-04T14:00:00",
    "escalated_at": "",
    "controlled_at": "",
    "resolved_at": "",
    "lifecycle_stage": "detected"
  },
  {
    "event_id": "RE-20260701-001",
    "event_name": "杨枝甘露椰乳分层沉淀",
    "product_id": "P04",
    "issue_type": "IT03",
    "risk_level": "medium",
    "risk_score": 5,
    "suspected_cause": "芒果汁中果酸导致椰乳蛋白质变性，加之西米淀粉糊化不完全产生沉淀",
    "linked_supplier": ["SUP03", "SUP07"],
    "linked_batch": ["BAT-20260625-001"],
    "recommended_action": ["CA-20260701-001", "CA-20260701-002"],
    "raw_feedback_count": 22,
    "feedback_keywords": ["分层", "沉淀", "椰乳", "结块", "口感差"],
    "aggregated_at": "2026-07-01T10:00:00",
    "detected_at": "2026-06-28T14:00:00",
    "escalated_at": "2026-06-30T09:00:00",
    "controlled_at": "2026-07-01T16:00:00",
    "resolved_at": "2026-07-10T18:00:00",
    "lifecycle_stage": "resolved"
  },
  {
    "event_id": "RE-20260710-001",
    "event_name": "百香果绿茶果籽被误认为异物",
    "product_id": "P05",
    "issue_type": "IT05",
    "risk_level": "low",
    "risk_score": 3,
    "suspected_cause": "消费者不了解百香果籽外观，误认为虫卵或异物",
    "linked_supplier": ["SUP09"],
    "linked_batch": ["BAT-20260705-001"],
    "recommended_action": ["CA-20260710-001"],
    "raw_feedback_count": 15,
    "feedback_keywords": ["虫子", "异物", "颗粒", "黑色的东西", "不敢喝"],
    "aggregated_at": "2026-07-10T11:00:00",
    "detected_at": "2026-07-08T09:00:00",
    "escalated_at": "",
    "controlled_at": "2026-07-10T14:00:00",
    "resolved_at": "2026-07-15T18:00:00",
    "lifecycle_stage": "resolved"
  },
  {
    "event_id": "RE-20260720-001",
    "event_name": "芝士莓莓草莓农残预警",
    "product_id": "P06",
    "issue_type": "IT08",
    "risk_level": "high",
    "risk_score": 11,
    "suspected_cause": "供应商J提供的草莓农残检测超标，存在食品安全隐患",
    "linked_supplier": ["SUP10"],
    "linked_batch": ["BAT-20260715-001"],
    "recommended_action": ["CA-20260720-001", "CA-20260720-002", "CA-20260720-003"],
    "raw_feedback_count": 8,
    "feedback_keywords": ["味道不对", "化学味", "头晕", "恶心", "不新鲜"],
    "aggregated_at": "2026-07-20T09:00:00",
    "detected_at": "2026-07-18T16:00:00",
    "escalated_at": "2026-07-19T08:00:00",
    "controlled_at": "2026-07-20T12:00:00",
    "resolved_at": "2026-07-28T18:00:00",
    "lifecycle_stage": "resolved"
  },
  {
    "event_id": "RE-20260801-001",
    "event_name": "芝士莓莓奶盖塌陷投诉",
    "product_id": "P06",
    "issue_type": "IT09",
    "risk_level": "medium",
    "risk_score": 5,
    "suspected_cause": "夏季高温导致奶盖结构不稳定，出杯后快速塌陷融化",
    "linked_supplier": ["SUP06"],
    "linked_batch": ["BAT-20260728-001"],
    "recommended_action": ["CA-20260801-001"],
    "raw_feedback_count": 25,
    "feedback_keywords": ["塌了", "融化", "消泡", "没有奶盖了", "流下来了"],
    "aggregated_at": "2026-08-01T10:00:00",
    "detected_at": "2026-07-29T14:00:00",
    "escalated_at": "2026-07-31T09:00:00",
    "controlled_at": "2026-08-01T16:00:00",
    "resolved_at": "",
    "lifecycle_stage": "controlled"
  },
  {
    "event_id": "RE-20260810-001",
    "event_name": "芋泥啵啵珍珠品质异常",
    "product_id": "P08",
    "issue_type": "IT10",
    "risk_level": "medium",
    "risk_score": 6,
    "suspected_cause": "珍珠煮制工艺不标准，部分门店煮制时间不足导致硬芯",
    "linked_supplier": ["SUP12"],
    "linked_batch": ["BAT-20260805-001"],
    "recommended_action": ["CA-20260810-001", "CA-20260810-002"],
    "raw_feedback_count": 30,
    "feedback_keywords": ["太硬", "硬芯", "不Q弹", "粘连", "像塑料"],
    "aggregated_at": "2026-08-10T11:00:00",
    "detected_at": "2026-08-08T09:00:00",
    "escalated_at": "2026-08-09T10:00:00",
    "controlled_at": "2026-08-10T15:00:00",
    "resolved_at": "",
    "lifecycle_stage": "controlled"
  },
  {
    "event_id": "RE-20260820-001",
    "event_name": "花生奶昔霉变过敏事件",
    "product_id": "P12",
    "issue_type": "IT06",
    "risk_level": "high",
    "risk_score": 12,
    "suspected_cause": "供应商Q提供的花生储存条件不当导致黄曲霉毒素超标，多名消费者出现过敏反应",
    "linked_supplier": ["SUP17"],
    "linked_batch": ["BAT-20260815-001"],
    "recommended_action": ["CA-20260820-001", "CA-20260820-002", "CA-20260820-003"],
    "raw_feedback_count": 12,
    "feedback_keywords": ["哈喇味", "苦味", "过敏", "恶心", "痒", "呕吐"],
    "aggregated_at": "2026-08-20T08:00:00",
    "detected_at": "2026-08-18T16:00:00",
    "escalated_at": "2026-08-19T08:00:00",
    "controlled_at": "2026-08-20T10:00:00",
    "resolved_at": "",
    "lifecycle_stage": "controlled"
  },
  {
    "event_id": "RE-20260901-001",
    "event_name": "冰博克拿铁冷链断裂微生物超标",
    "product_id": "P07",
    "issue_type": "IT06",
    "risk_level": "high",
    "risk_score": 10,
    "suspected_cause": "华东仓冷链设备故障导致鲜奶温度超标，多名消费者出现肠胃不适",
    "linked_supplier": ["SUP06"],
    "linked_batch": ["BAT-20260828-001"],
    "recommended_action": ["CA-20260901-001", "CA-20260901-002"],
    "raw_feedback_count": 18,
    "feedback_keywords": ["拉肚子", "肚子疼", "呕吐", "异味", "酸了", "变质"],
    "aggregated_at": "2026-09-01T09:00:00",
    "detected_at": "2026-08-30T14:00:00",
    "escalated_at": "2026-08-31T08:00:00",
    "controlled_at": "2026-09-01T12:00:00",
    "resolved_at": "",
    "lifecycle_stage": "controlled"
  },
  {
    "event_id": "RE-20260910-001",
    "event_name": "百香果绿茶茶底过萃苦涩",
    "product_id": "P05",
    "issue_type": "IT11",
    "risk_level": "medium",
    "risk_score": 5,
    "suspected_cause": "夏季门店制茶时浸泡时间过长导致茶底过萃，苦涩味明显",
    "linked_supplier": ["SUP01"],
    "linked_batch": ["BAT-20260905-001"],
    "recommended_action": ["CA-20260910-001"],
    "raw_feedback_count": 20,
    "feedback_keywords": ["苦", "苦涩", "像中药", "茶味太重", "发苦"],
    "aggregated_at": "2026-09-10T10:00:00",
    "detected_at": "2026-09-08T09:00:00",
    "escalated_at": "",
    "controlled_at": "2026-09-10T14:00:00",
    "resolved_at": "2026-09-15T18:00:00",
    "lifecycle_stage": "resolved"
  },
  {
    "event_id": "RE-20261001-001",
    "event_name": "多门店甜度失控投诉",
    "product_id": "P08",
    "issue_type": "IT11",
    "risk_level": "medium_high",
    "risk_score": 7,
    "suspected_cause": "糖浆泵头老化导致出糖量不稳定，多门店出现甜度异常",
    "linked_supplier": ["SUP13"],
    "linked_batch": ["BAT-20260928-001"],
    "recommended_action": ["CA-20261001-001", "CA-20261001-002"],
    "raw_feedback_count": 35,
    "feedback_keywords": ["太甜", "不够甜", "没味道", "甜死了", "像白水"],
    "aggregated_at": "2026-10-01T09:00:00",
    "detected_at": "2026-09-28T14:00:00",
    "escalated_at": "2026-09-30T10:00:00",
    "controlled_at": "2026-10-01T16:00:00",
    "resolved_at": "",
    "lifecycle_stage": "controlled"
  }
]